eco_back/__init__.py
eco_back/api/__init__.py
eco_back/api/client.py
eco_back/api/config.py
eco_back/api/registro.py
eco_back/database/__init__.py
eco_back/database/config.py
eco_back/database/connection.py
eco_back/database/models.py
eco_back/database/postgis.py
eco_back/database/repository.py
eco_back/documento/__init__.py
eco_back/documento/anexos.py
eco_back/registro/__init__.py
eco_back/registro/trazabilidad.py
eco_back/utils/__init__.py
eco_back/utils/exceptions.py
eco_back/utils/logger_generico.py
eco_back-0.2.4.dist-info/licenses/LICENSE
eco_back-0.2.4.dist-info/METADATA
eco_back-0.2.4.dist-info/WHEEL
eco_back-0.2.4.dist-info/top_level.txt
eco_back-0.2.4.dist-info/RECORD
