Metadata-Version: 2.4
Name: eco-back
Version: 0.2.4
Summary: Librería Python eco-back
Author-email: EI UNP <ecosistema@unp.gov.co>
License: MIT
Project-URL: Homepage, https://github.com/EcosistemaUNP/eco-back
Project-URL: Documentation, https://github.com/EcosistemaUNP/eco-back
Project-URL: Repository, https://github.com/EcosistemaUNP/eco-back
Project-URL: Bug Tracker, https://github.com/EcosistemaUNP/eco-back/issues
Classifier: Development Status :: 3 - Alpha
Classifier: Intended Audience :: Developers
Classifier: License :: OSI Approved :: MIT License
Classifier: Programming Language :: Python :: 3
Classifier: Programming Language :: Python :: 3.8
Classifier: Programming Language :: Python :: 3.9
Classifier: Programming Language :: Python :: 3.10
Classifier: Programming Language :: Python :: 3.11
Classifier: Programming Language :: Python :: 3.12
Requires-Python: >=3.8
License-File: LICENSE
Requires-Dist: psycopg2-binary>=2.9.0
Requires-Dist: geoalchemy2>=0.14.0
Requires-Dist: requests>=2.31.0
Requires-Dist: djangorestframework>=3.14.0
Requires-Dist: django>=4.0.0
Provides-Extra: dev
Requires-Dist: pytest>=7.0; extra == "dev"
Requires-Dist: pytest-cov>=4.0; extra == "dev"
Requires-Dist: black>=23.0; extra == "dev"
Requires-Dist: flake8>=6.0; extra == "dev"
Requires-Dist: mypy>=1.0; extra == "dev"
Requires-Dist: pytest-mock>=3.12.0; extra == "dev"
Provides-Extra: geo
Requires-Dist: shapely>=2.0.0; extra == "geo"
Requires-Dist: geojson>=3.0.0; extra == "geo"
Dynamic: license-file
